js_lib_select2/__init__.py
js_lib_select2/apps.py
js_lib_select2/static/js_lib_select2/css/select2.css
js_lib_select2/static/js_lib_select2/css/select2.min.css
js_lib_select2/static/js_lib_select2/js/select2.full.js
js_lib_select2/static/js_lib_select2/js/select2.full.min.js
js_lib_select2/static/js_lib_select2/js/select2.js
js_lib_select2/static/js_lib_select2/js/select2.min.js
js_lib_select2/static/js_lib_select2/js/i18n/af.js
js_lib_select2/static/js_lib_select2/js/i18n/ar.js
js_lib_select2/static/js_lib_select2/js/i18n/az.js
js_lib_select2/static/js_lib_select2/js/i18n/bg.js
js_lib_select2/static/js_lib_select2/js/i18n/bn.js
js_lib_select2/static/js_lib_select2/js/i18n/bs.js
js_lib_select2/static/js_lib_select2/js/i18n/ca.js
js_lib_select2/static/js_lib_select2/js/i18n/cs.js
js_lib_select2/static/js_lib_select2/js/i18n/da.js
js_lib_select2/static/js_lib_select2/js/i18n/de.js
js_lib_select2/static/js_lib_select2/js/i18n/dsb.js
js_lib_select2/static/js_lib_select2/js/i18n/el.js
js_lib_select2/static/js_lib_select2/js/i18n/en.js
js_lib_select2/static/js_lib_select2/js/i18n/es.js
js_lib_select2/static/js_lib_select2/js/i18n/et.js
js_lib_select2/static/js_lib_select2/js/i18n/eu.js
js_lib_select2/static/js_lib_select2/js/i18n/fa.js
js_lib_select2/static/js_lib_select2/js/i18n/fi.js
js_lib_select2/static/js_lib_select2/js/i18n/fr.js
js_lib_select2/static/js_lib_select2/js/i18n/gl.js
js_lib_select2/static/js_lib_select2/js/i18n/he.js
js_lib_select2/static/js_lib_select2/js/i18n/hi.js
js_lib_select2/static/js_lib_select2/js/i18n/hr.js
js_lib_select2/static/js_lib_select2/js/i18n/hsb.js
js_lib_select2/static/js_lib_select2/js/i18n/hu.js
js_lib_select2/static/js_lib_select2/js/i18n/hy.js
js_lib_select2/static/js_lib_select2/js/i18n/id.js
js_lib_select2/static/js_lib_select2/js/i18n/is.js
js_lib_select2/static/js_lib_select2/js/i18n/it.js
js_lib_select2/static/js_lib_select2/js/i18n/ja.js
js_lib_select2/static/js_lib_select2/js/i18n/ka.js
django_js_lib_select2-4.0.13.0.dist-info/LICENSE
django_js_lib_select2-4.0.13.0.dist-info/WHEEL
django_js_lib_select2-4.0.13.0.dist-info/METADATA
django_js_lib_select2-4.0.13.0.dist-info/RECORD
