Metadata-Version: 2.1
Name: django-js-lib-select2
Version: 4.0.13.0
Summary: Select2 for Django
Requires-Python: >=3.8
Classifier: License :: OSI Approved :: MIT License
